dump_xml/__init__.py
dump_xml-1.0.0.dist-info/METADATA
dump_xml-1.0.0.dist-info/WHEEL
dump_xml-1.0.0.dist-info/top_level.txt
dump_xml-1.0.0.dist-info/RECORD
