Metadata-Version: 2.1
Name: dump-xml
Version: 1.0.0
Summary: A simple dictionary to XML converter that "Just Works".
Home-page: https://github.com/intouch-smartwater/dump_xml
Author: James Cheese
Author-email: james.cheese@intouch-ltd.com
License: MIT
Platform: UNKNOWN
Classifier: Development Status :: 5 - Production/Stable
Classifier: Intended Audience :: Developers
Classifier: License :: OSI Approved :: MIT License
Classifier: Programming Language :: Python
Classifier: Programming Language :: Python :: 2
Classifier: Programming Language :: Python :: 2.7
Classifier: Programming Language :: Python :: 3
Classifier: Programming Language :: Python :: 3.4
Classifier: Programming Language :: Python :: 3.5
Classifier: Programming Language :: Python :: 3.6
Classifier: Programming Language :: Python :: 3.7
